heimdall/connectors/mariadb_get.py
pyheimdall_mariadb-1.1.1.dist-info/METADATA
pyheimdall_mariadb-1.1.1.dist-info/WHEEL
pyheimdall_mariadb-1.1.1.dist-info/licenses/LICENSE
pyheimdall_mariadb-1.1.1.dist-info/RECORD
