Metadata-Version: 2.4
Name: pyheimdall-mariadb
Version: 1.1.1
Summary: MariaDB connector for pyHeimdall
Project-URL: Homepage, https://gitlab.huma-num.fr/datasphere/heimdall/connectors/mariadb/
Project-URL: Issues, https://gitlab.huma-num.fr/datasphere/heimdall/python/-/issues
Author-email: Régis Witz <regis.witz@cnrs.fr>
License: aGPL
License-File: LICENSE
Keywords: databases,hera,interoperability
Classifier: Development Status :: 3 - Alpha
Classifier: Environment :: Console
Classifier: License :: OSI Approved :: GNU Affero General Public License v3 or later (AGPLv3+)
Classifier: Operating System :: OS Independent
Classifier: Programming Language :: Python :: 3
Classifier: Topic :: Database
Classifier: Topic :: Documentation
Classifier: Topic :: File Formats
Classifier: Topic :: Scientific/Engineering
Classifier: Topic :: Utilities
Requires-Dist: mariadb
Requires-Dist: pyheimdall>1.0.0
Provides-Extra: dev
Requires-Dist: pyheimdall[pep-8,tests]; extra == 'dev'
Provides-Extra: pep-8
Requires-Dist: pycodestyle; extra == 'pep-8'
Provides-Extra: tests
Requires-Dist: coverage; extra == 'tests'
Requires-Dist: pytest; extra == 'tests'
